_crosshair_tracers.cpython-314-darwin.so
crosshair/_tracers_pycompat.h
crosshair/pure_importer.py
crosshair/options.py
crosshair/lsp_server_test.py
crosshair/conftest.py
crosshair/copyext_test.py
crosshair/objectproxy.py
crosshair/pathing_oracle_test.py
crosshair/objectproxy_test.py
crosshair/stubs_parser.py
crosshair/_preliminaries_test.py
crosshair/dynamic_typing_test.py
crosshair/enforce.py
crosshair/path_search_test.py
crosshair/condition_parser.py
crosshair/util.py
crosshair/dynamic_typing.py
crosshair/register_contract.py
crosshair/tracers.py
crosshair/_tracers.h
crosshair/type_repo.py
crosshair/fnutil.py
crosshair/unicode_categories.py
crosshair/copyext.py
crosshair/_tracers_test.py
crosshair/__init__.py
crosshair/core.py
crosshair/path_cover.py
crosshair/enforce_test.py
crosshair/test_util.py
crosshair/core_test.py
crosshair/codeconfig.py
crosshair/util_test.py
crosshair/watcher_test.py
crosshair/auditwall.py
crosshair/simplestructs_test.py
crosshair/z3util_test.py
crosshair/diff_behavior.py
crosshair/condition_parser_test.py
crosshair/pure_importer_test.py
crosshair/fnutil_test.py
crosshair/stubs_parser_test.py
crosshair/options_test.py
crosshair/patch_equivalence_test.py
crosshair/abcstring.py
crosshair/_mark_stacks.h
crosshair/fuzz_core_test.py
crosshair/unicode_categories_test.py
crosshair/statespace_test.py
crosshair/py.typed
crosshair/lsp_server.py
crosshair/path_search.py
crosshair/auditwall_test.py
crosshair/smtlib_test.py
crosshair/register_contract_test.py
crosshair/statespace.py
crosshair/opcode_intercept_test.py
crosshair/main_test.py
crosshair/codeconfig_test.py
crosshair/watcher.py
crosshair/test_util_test.py
crosshair/opcode_intercept.py
crosshair/simplestructs.py
crosshair/tracers_test.py
crosshair/smtlib.py
crosshair/main.py
crosshair/path_cover_test.py
crosshair/__main__.py
crosshair/pathing_oracle.py
crosshair/diff_behavior_test.py
crosshair/core_and_libs.py
crosshair_tool-0.0.102.dist-info/RECORD
crosshair_tool-0.0.102.dist-info/WHEEL
crosshair_tool-0.0.102.dist-info/entry_points.txt
crosshair_tool-0.0.102.dist-info/top_level.txt
crosshair_tool-0.0.102.dist-info/METADATA
crosshair_tool-0.0.102.dist-info/licenses/LICENSE
