Metadata-Version: 2.1
Name: crosshair-tool
Version: 0.0.102
Summary: Analyze Python code for correctness using symbolic execution.
Home-page: https://github.com/pschanely/CrossHair
Author: Phillip Schanely
Author-email: pschanely+vE7F@gmail.com
License: MIT
Classifier: Development Status :: 3 - Alpha
Classifier: Intended Audience :: Developers
Classifier: Operating System :: OS Independent
Classifier: Programming Language :: Python :: 3
Classifier: Programming Language :: Python :: 3.8
Classifier: Programming Language :: Python :: 3.9
Classifier: Programming Language :: Python :: 3.10
Classifier: Programming Language :: Python :: 3.11
Classifier: Programming Language :: Python :: 3.12
Classifier: Programming Language :: Python :: 3.13
Classifier: Programming Language :: Python :: Implementation :: CPython
Classifier: Topic :: Software Development :: Quality Assurance
Classifier: Topic :: Software Development :: Testing
Requires-Python: >=3.8
License-File: LICENSE
Requires-Dist: packaging
Requires-Dist: typing-inspect >=0.7.1
Requires-Dist: typing-extensions >=3.10.0
Requires-Dist: z3-solver >=4.13.0.0
Requires-Dist: importlib-metadata >=4.0.0
Requires-Dist: pygls >=1.0.0
Requires-Dist: typeshed-client >=2.0.5
Provides-Extra: dev
Requires-Dist: autodocsumm <1,>=0.2.2 ; extra == 'dev'
Requires-Dist: black ==25.9.0 ; extra == 'dev'
Requires-Dist: deal >=4.13.0 ; extra == 'dev'
Requires-Dist: icontract >=2.4.0 ; extra == 'dev'
Requires-Dist: isort ==5.11.5 ; extra == 'dev'
Requires-Dist: mypy ==1.18.1 ; extra == 'dev'
Requires-Dist: pre-commit ~=2.20 ; extra == 'dev'
Requires-Dist: pytest ; extra == 'dev'
Requires-Dist: pytest-xdist ; extra == 'dev'
Requires-Dist: setuptools ; extra == 'dev'
Requires-Dist: sphinx >=3.4.3 ; extra == 'dev'
Requires-Dist: sphinx-rtd-theme >=0.5.1 ; extra == 'dev'
Requires-Dist: rst2pdf >=0.102 ; extra == 'dev'
Requires-Dist: z3-solver ==4.15.4.0 ; extra == 'dev'
Requires-Dist: numpy ==1.24.0 ; (python_version < "3.12") and extra == 'dev'
Requires-Dist: numpy ==2.3.3 ; (python_version >= "3.12") and extra == 'dev'
